pandit.py
pandit-0.0.10.dist-info/LICENSE
pandit-0.0.10.dist-info/METADATA
pandit-0.0.10.dist-info/WHEEL
pandit-0.0.10.dist-info/top_level.txt
pandit-0.0.10.dist-info/RECORD
