Metadata-Version: 2.1
Name: pandit
Version: 0.0.10
Summary: Pandas with some cool additional features
Home-page: https://github.com/sileod/pandit
Author: sileod
License: GPL
License-File: LICENSE
Requires-Dist: pandas
